{
  "blocked": true,
  "close_run_status": "REOPENED_EXCEPTION",
  "deterministic_replay": true,
  "evidence_hash": "db089f352bf6bcf6270ecb7f9181b07395538316154fa5567524d1d54395ff0d",
  "first_counts": {
    "journal_entries": 1,
    "journal_entry_lines": 2,
    "missing_lines": 0
  },
  "first_manifest_hash": "fcfaf5e070409dc45dad7201996b4e99d76463f9782ba85d50fd018a3b2a147f",
  "generated_at": "2026-03-09T04:30:31.096641+00:00",
  "go_live_passed": true,
  "manifest_hash": "fcfaf5e070409dc45dad7201996b4e99d76463f9782ba85d50fd018a3b2a147f",
  "passed": true,
  "pilot_scope": {
    "company_id": 5
  },
  "posting_first": {
    "approved": 0,
    "attempted": 0,
    "errors": [],
    "failed": 0,
    "posted": 0,
    "skipped": 0
  },
  "posting_second": {
    "approved": 0,
    "attempted": 0,
    "errors": [],
    "failed": 0,
    "posted": 0,
    "skipped": 0
  },
  "revaluation_run_id": "c22a38c6-7c0b-4b4a-8588-b98e970dd929",
  "run_id": "00000000-0000-0000-0000-000000000701",
  "schema_version": 1,
  "second_counts": {
    "journal_entries": 1,
    "journal_entry_lines": 2,
    "missing_lines": 0
  },
  "second_manifest_hash": "fcfaf5e070409dc45dad7201996b4e99d76463f9782ba85d50fd018a3b2a147f",
  "signature": "db089f352bf6bcf6270ecb7f9181b07395538316154fa5567524d1d54395ff0d",
  "signature_type": "sha256"
}