{
  "company_id": 5,
  "cycle": {
    "closed": 0,
    "company_id": 5,
    "confirmed": 0,
    "differences": 0,
    "disputed": 0,
    "generated_at": "2026-03-10T00:21:22.642469+00:00",
    "issues": [],
    "issues_count": 0,
    "open_items": 0,
    "processed": 0,
    "schema_version": 1
  },
  "cycle_passed": true,
  "dispatch": {
    "attempted": 1,
    "failed": 0,
    "retried": 0,
    "sent": 1
  },
  "evidence_hash": "5636db1cf61bcc8f76db3b17600dc2bfabe6a14b7755df1e20c7826c22b34907",
  "generated_at": "2026-03-10T00:21:22.658558+00:00",
  "schema_version": 1,
  "signature": "5636db1cf61bcc8f76db3b17600dc2bfabe6a14b7755df1e20c7826c22b34907",
  "signature_type": "sha256",
  "strict": true
}